<?xml version="1.0" encoding="utf-8"?>
<media>
	<media>
		<title>beIN SPORTS HABER Canlı Yayını | #beINSPORTS</title>
		<thumb>https://i.ytimg.com/vi/9xVXWLwT0vA/hqdefault_live.jpg</thumb>
		<type>youtube</type>
		<src>9xVXWLwT0vA</src>
	</media>
	<media>
		<title>🔴Galatasaray - Fenerbahçe Maç Özetleri | beIN SPORTS Arşiv</title>
		<thumb>https://i.ytimg.com/vi/D6JUgHh4vPk/hqdefault_live.jpg</thumb>
		<type>youtube</type>
		<src>D6JUgHh4vPk</src>
	</media>
	<media>
		<title>A Spor Canlı Yayın 🔴</title>
		<thumb>https://i.ytimg.com/vi/mDTnFqGLLs4/hqdefault_live.jpg</thumb>
		<type>youtube</type>
		<src>mDTnFqGLLs4</src>
	</media>
	<media>
		<title>#CANLI | HT Spor 7/24 Canlı Yayını</title>
		<thumb>https://i.ytimg.com/vi/ih2KAtA50I4/hqdefault_live.jpg</thumb>
		<type>youtube</type>
		<src>ih2KAtA50I4</src>
	</media>
	<media>
		<title>SIFIR TV CANLI YAYIN</title>
		<thumb>https://i.ytimg.com/vi/CpTQkef3BfY/hqdefault_live.jpg</thumb>
		<type>youtube</type>
		<src>CpTQkef3BfY</src>
	</media>
	<media>
		<title>Start Kura Çekimi  Şanlıurfa</title>
		<thumb>https://i.ytimg.com/vi/oiR4SeeTZ1I/hqdefault_live.jpg</thumb>
		<type>youtube</type>
		<src>oiR4SeeTZ1I</src>
	</media>
	<media>
		<title>TJK TV Canlı Yayın</title>
		<thumb>https://i.ytimg.com/vi/g89RQMJtK6E/hqdefault_live.jpg</thumb>
		<type>youtube</type>
		<src>g89RQMJtK6E</src>
	</media>
	<media>
		<title>Start Kura Çekimi  Bursa</title>
		<thumb>https://i.ytimg.com/vi/i5CgnroZ1HY/hqdefault_live.jpg</thumb>
		<type>youtube</type>
		<src>i5CgnroZ1HY</src>
	</media>
</media>