<?xml version="1.0" encoding="utf-8"?>
<media>
	<media>
		<title>beIN SPORTS HABER Canlı Yayını | #beINSPORTS</title>
		<thumb>https://i.ytimg.com/vi/i7UpPgxfZZ8/hqdefault_live.jpg</thumb>
		<type>youtube</type>
		<src>i7UpPgxfZZ8</src>
	</media>
	<media>
		<title>🔴 2025-2026 Sezonu Derbi Maç Özetleri | beIN SPORTS Arşiv</title>
		<thumb>https://i.ytimg.com/vi/vTPsolQFr5s/hqdefault_live.jpg</thumb>
		<type>youtube</type>
		<src>vTPsolQFr5s</src>
	</media>
	<media>
		<title>A Spor Canlı Yayın 🔴</title>
		<thumb>https://i.ytimg.com/vi/-zSaswVrQ_M/hqdefault_live.jpg</thumb>
		<type>youtube</type>
		<src>-zSaswVrQ_M</src>
	</media>
	<media>
		<title>#CANLI | Deniz Biricik İle Satır Arası</title>
		<thumb>https://i.ytimg.com/vi/gcWaPe_LBMc/hqdefault_live.jpg</thumb>
		<type>youtube</type>
		<src>gcWaPe_LBMc</src>
	</media>
	<media>
		<title>Start Kura Çekimi Ankara</title>
		<thumb>https://i.ytimg.com/vi/H3eff90RTg4/hqdefault_live.jpg</thumb>
		<type>youtube</type>
		<src>H3eff90RTg4</src>
	</media>
	<media>
		<title>TJK TV Eyerleme Alanı Ankara</title>
		<thumb>https://i.ytimg.com/vi/s0gwktXASMo/hqdefault_live.jpg</thumb>
		<type>youtube</type>
		<src>s0gwktXASMo</src>
	</media>
	<media>
		<title>Start Kura Çekimi İzmir</title>
		<thumb>https://i.ytimg.com/vi/o9jIU9Omu6E/hqdefault_live.jpg</thumb>
		<type>youtube</type>
		<src>o9jIU9Omu6E</src>
	</media>
	<media>
		<title>Start Kura Çekimi Diyarbakır</title>
		<thumb>https://i.ytimg.com/vi/Dczgxl7wjcQ/hqdefault_live.jpg</thumb>
		<type>youtube</type>
		<src>Dczgxl7wjcQ</src>
	</media>
	<media>
		<title>TJK TV Canlı Yayın</title>
		<thumb>https://i.ytimg.com/vi/g89RQMJtK6E/hqdefault_live.jpg</thumb>
		<type>youtube</type>
		<src>g89RQMJtK6E</src>
	</media>
</media>